setup.py
wae/__init__.py
wae/app.py
wae/cgis.py
wae/config.py
wae/connect.py
wae/context.py
wae/dbobj.py
wae/format.py
wae/httprequest.py
wae/httpresponse.py
wae/job.py
wae/mailer.py
wae/mgobj.py
wae/middleware.py
wae/parellelquery.py
wae/pdo.py
wae/session.py
wae/signal.py
wae/sqlbuilder.py
wae/template.py
wae/user.py
wae/utils.py
wae/websocket.py
wae.egg-info/PKG-INFO
wae.egg-info/SOURCES.txt
wae.egg-info/dependency_links.txt
wae.egg-info/top_level.txt