Metadata-Version: 1.0
Name: wae
Version: 0.1a12
Summary: Web Application Engine
Home-page: UNKNOWN
Author: johnray
Author-email: nuphahuang@gmail.com
License: UNKNOWN
Platform: UNKNOWN
